spike2loader/__init__.py
spike2loader/spike2loader.py
spike2loader-0.5.dist-info/LICENSE.txt
spike2loader-0.5.dist-info/METADATA
spike2loader-0.5.dist-info/WHEEL
spike2loader-0.5.dist-info/entry_points.txt
spike2loader-0.5.dist-info/top_level.txt
spike2loader-0.5.dist-info/RECORD
