Metadata-Version: 2.1
Name: spike2loader
Version: 0.5
Summary: Reads smrx (spike2) files as pandas dataframes
Home-page: https://github.com/JulienBrn/Spike2Loader
Download-URL: https://github.com/JulienBrn/Spike2Loader.git
Author: Julien Braine
Author-email: julienbraine@yahoo.fr
License: MIT
Keywords: python,logging
License-File: LICENSE.txt
Requires-Dist: pandas
Requires-Dist: sonpy
Requires-Dist: beautifullogger
Requires-Dist: tqdm
